tutti_aisthetics_slim/__init__.py
tutti_aisthetics_slim/score.py
tutti_aisthetics_slim/model/model.pb
tutti_aisthetics_slim-0.2.0.dist-info/LICENSE
tutti_aisthetics_slim-0.2.0.dist-info/METADATA
tutti_aisthetics_slim-0.2.0.dist-info/WHEEL
tutti_aisthetics_slim-0.2.0.dist-info/top_level.txt
tutti_aisthetics_slim-0.2.0.dist-info/zip-safe
tutti_aisthetics_slim-0.2.0.dist-info/RECORD
